tinyhmm/__init__.py
tinyhmm/__main__.py
tinyhmm/_version.py
tinyhmm/cli.py
tinyhmm-0.0.1.dist-info/AUTHORS.rst
tinyhmm-0.0.1.dist-info/LICENSE
tinyhmm-0.0.1.dist-info/METADATA
tinyhmm-0.0.1.dist-info/WHEEL
tinyhmm-0.0.1.dist-info/entry_points.txt
tinyhmm-0.0.1.dist-info/top_level.txt
tinyhmm-0.0.1.dist-info/RECORD
