Metadata-Version: 2.1
Name: tinyhmm
Version: 0.0.1
Summary: A tiny hmm.
Home-page: https://github.com/reedf1/tinyhmm
Author: Reed Roberts
Author-email: reedf1@gmail.com
License: MIT
Project-URL: Documentation, https://tinyhmm.readthedocs.io/
Project-URL: Changelog, https://tinyhmm.readthedocs.io/en/latest/changelog.html
Project-URL: Issue Tracker, https://github.com/reedf1/tinyhmm/issues
Platform: UNKNOWN
Classifier: Development Status :: 5 - Production/Stable
Classifier: Intended Audience :: Developers
Classifier: License :: OSI Approved :: MIT License
Classifier: Operating System :: Unix
Classifier: Operating System :: POSIX
Classifier: Operating System :: Microsoft :: Windows
Classifier: Programming Language :: Python
Classifier: Programming Language :: Python :: 3
Classifier: Programming Language :: Python :: 3 :: Only
Classifier: Programming Language :: Python :: 3.7
Classifier: Programming Language :: Python :: 3.8
Classifier: Programming Language :: Python :: 3.9
Classifier: Programming Language :: Python :: 3.10
Classifier: Programming Language :: Python :: 3.11
Classifier: Programming Language :: Python :: Implementation :: CPython
Classifier: Programming Language :: Python :: Implementation :: PyPy
Classifier: Topic :: Utilities
Requires-Python: >=3.7
License-File: LICENSE
License-File: AUTHORS.rst
